{
    "special":[
       {
          "imagename":"Autobomb_Launcher.png",
          "name":"Autobomb Launcher"
       },
       {
          "imagename":"Baller.png",
          "name":"Baller"
       },
       {
          "imagename":"Booyah_Bomb.png",
          "name":"Booyah Bomb"
       },
       {
          "imagename":"Bubble_Blower.png",
          "name":"Bubble Blower"
       },
       {
          "imagename":"Burst-Bomb_Launcher.png",
          "name":"Burst-Bomb Launcher"
       },
       {
          "imagename":"Curling-Bomb_Launcher.png",
          "name":"Curling-Bomb Launcher"
       },
       {
          "imagename":"Ink_Armor.png",
          "name":"Ink Armor"
       },
       {
          "imagename":"Ink_Storm.png",
          "name":"Ink Storm"
       },
       {
          "imagename":"Inkjet.png",
          "name":"Inkjet"
       },
       {
          "imagename":"Princess_Cannon.png",
          "name":"Princess Cannon"
       },
       {
          "imagename":"Splashdown.png",
          "name":"Splashdown"
       },
       {
          "imagename":"Splat-Bomb_Launcher.png",
          "name":"Splat-Bomb Launcher"
       },
       {
          "imagename":"Sting_Ray.png",
          "name":"Sting Ray"
       },
       {
          "imagename":"Suction-Bomb_Launcher.png",
          "name":"Suction-Bomb Launcher"
       },
       {
          "imagename":"Tenta_Missiles.png",
          "name":"Tenta Missiles"
       },
       {
          "imagename":"Ultra_Stamp.png",
          "name":"Ultra Stamp"
       }
    ],
    "sub":[
       {
          "imagename":"Autobomb.png",
          "name":"Autobomb"
       },
       {
          "imagename":"Burst_Bomb.png",
          "name":"Burst Bomb"
       },
       {
          "imagename":"Curling_Bomb.png",
          "name":"Curling Bomb"
       },
       {
          "imagename":"Fizzy_Bomb.png",
          "name":"Fizzy Bomb"
       },
       {
          "imagename":"Ink_Mine.png",
          "name":"Ink Mine"
       },
       {
          "imagename":"Point_Sensor.png",
          "name":"Point Sensor"
       },
       {
          "imagename":"Splash_Wall.png",
          "name":"Splash Wall"
       },
       {
          "imagename":"Splat_Bomb.png",
          "name":"Splat Bomb"
       },
       {
          "imagename":"Sprinkler.png",
          "name":"Sprinkler"
       },
       {
          "imagename":"Squid_Beakon.png",
          "name":"Squid Beakon"
       },
       {
          "imagename":"Suction_Bomb.png",
          "name":"Suction Bomb"
       },
       {
          "imagename":"Torpedo.png",
          "name":"Torpedo"
       },
       {
          "imagename":"Toxic_Mist.png",
          "name":"Toxic Mist"
       }
    ],
    "main":[
       {
          "specialweapon":"Sting Ray",
          "imagename":"52_Gal_Deco.png",
          "name":".52 Gal Deco",
          "subweapon":"Curling Bomb"
       },
       {
          "specialweapon":"Baller",
          "imagename":"52_Gal.png",
          "name":".52 Gal",
          "subweapon":"Point Sensor"
       },
       {
          "specialweapon":"Splashdown",
          "imagename":"96_Gal_Deco.png",
          "name":".96 Gal Deco",
          "subweapon":"Splash Wall"
       },
       {
          "specialweapon":"Ink Armor",
          "imagename":"96_Gal.png",
          "name":".96 Gal",
          "subweapon":"Sprinkler"
       },
       {
          "specialweapon":"Curling-Bomb Launcher",
          "imagename":"Aerospray_MG.png",
          "name":"Aerospray MG",
          "subweapon":"Suction Bomb"
       },
       {
          "specialweapon":"Booyah Bomb",
          "imagename":"Aerospray_PG.png",
          "name":"Aerospray PG",
          "subweapon":"Burst Bomb"
       },
       {
          "specialweapon":"Baller",
          "imagename":"Aerospray_RG.png",
          "name":"Aerospray RG",
          "subweapon":"Sprinkler"
       },
       {
          "specialweapon":"Ink Storm",
          "imagename":"Ballpoint_Splatling_Nouveau.png",
          "name":"Ballpoint Splatling Nouveau",
          "subweapon":"Squid Beakon"
       },
       {
          "specialweapon":"Inkjet",
          "imagename":"Ballpoint_Splatling.png",
          "name":"Ballpoint Splatling",
          "subweapon":"Toxic Mist"
       },
       {
          "specialweapon":"Tenta Missiles",
          "imagename":"Bamboozler_14_Mk_I.png",
          "name":"Bamboozler 14 Mk I",
          "subweapon":"Curling Bomb"
       },
       {
          "specialweapon":"Burst-Bomb Launcher",
          "imagename":"Bamboozler_14_Mk_II.png",
          "name":"Bamboozler 14 Mk II",
          "subweapon":"Toxic Mist"
       },
       {
          "specialweapon":"Bubble Blower",
          "imagename":"Bamboozler_14_Mk_III.png",
          "name":"Bamboozler 14 Mk III",
          "subweapon":"Fizzy Bomb"
       },
       {
          "specialweapon":"Splashdown",
          "imagename":"Blaster.png",
          "name":"Blaster",
          "subweapon":"Toxic Mist"
       },
       {
          "specialweapon":"Suction-Bomb Launcher",
          "imagename":"Bloblobber_Deco.png",
          "name":"Bloblobber Deco",
          "subweapon":"Sprinkler"
       },
       {
          "specialweapon":"Ink Storm",
          "imagename":"Bloblobber.png",
          "name":"Bloblobber",
          "subweapon":"Splash Wall"
       },
       {
          "specialweapon":"Autobomb Launcher",
          "imagename":"Carbon_Roller_Deco.png",
          "name":"Carbon Roller Deco",
          "subweapon":"Burst Bomb"
       },
       {
          "specialweapon":"Ink Storm",
          "imagename":"Carbon_Roller.png",
          "name":"Carbon Roller",
          "subweapon":"Autobomb"
       },
       {
          "specialweapon":"Bubble Blower",
          "imagename":"Cherry_H-3_Nozzlenose.png",
          "name":"Cherry H-3 Nozzlenose",
          "subweapon":"Splash Wall"
       },
       {
          "specialweapon":"Tenta Missiles",
          "imagename":"Clash_Blaster_Neo.png",
          "name":"Clash Blaster Neo",
          "subweapon":"Curling Bomb"
       },
       {
          "specialweapon":"Sting Ray",
          "imagename":"Clash_Blaster.png",
          "name":"Clash Blaster",
          "subweapon":"Splat Bomb"
       },
       {
          "specialweapon":"Ink Armor",
          "imagename":"Classic_Squiffer.png",
          "name":"Classic Squiffer",
          "subweapon":"Point Sensor"
       },
       {
          "specialweapon":"Splashdown",
          "imagename":"Clear_Dapple_Dualies.png",
          "name":"Clear Dapple Dualies",
          "subweapon":"Torpedo"
       },
       {
          "specialweapon":"Inkjet",
          "imagename":"Custom_Blaster.png",
          "name":"Custom Blaster",
          "subweapon":"Autobomb"
       },
       {
          "specialweapon":"Ink Storm",
          "imagename":"Custom_Dualie_Squelchers.png",
          "name":"Custom Dualie Squelchers",
          "subweapon":"Splat Bomb"
       },
       {
          "specialweapon":"Bubble Blower",
          "imagename":"Custom_E-liter_4K_Scope.png",
          "name":"Custom E-liter 4K Scope",
          "subweapon":"Squid Beakon"
       },
       {
          "specialweapon":"Bubble Blower",
          "imagename":"Custom_E-liter_4K.png",
          "name":"Custom E-liter 4K",
          "subweapon":"Squid Beakon"
       },
       {
          "specialweapon":"Baller",
          "imagename":"Custom_Explosher.png",
          "name":"Custom Explosher",
          "subweapon":"Point Sensor"
       },
       {
          "specialweapon":"Inkjet",
          "imagename":"Custom_Goo_Tuber.png",
          "name":"Custom Goo Tuber",
          "subweapon":"Curling Bomb"
       },
       {
          "specialweapon":"Ink Armor",
          "imagename":"Custom_Hydra_Splatling.png",
          "name":"Custom Hydra Splatling",
          "subweapon":"Ink Mine"
       },
       {
          "specialweapon":"Sting Ray",
          "imagename":"Custom_Jet_Squelcher.png",
          "name":"Custom Jet Squelcher",
          "subweapon":"Burst Bomb"
       },
       {
          "specialweapon":"Bubble Blower",
          "imagename":"Custom_Range_Blaster.png",
          "name":"Custom Range Blaster",
          "subweapon":"Curling Bomb"
       },
       {
          "specialweapon":"Ink Storm",
          "imagename":"Custom_Splattershot_Jr.png",
          "name":"Custom Splattershot Jr.",
          "subweapon":"Autobomb"
       },
       {
          "specialweapon":"Ink Storm",
          "imagename":"Dapple_Dualies_Nouveau.png",
          "name":"Dapple Dualies Nouveau",
          "subweapon":"Toxic Mist"
       },
       {
          "specialweapon":"Suction-Bomb Launcher",
          "imagename":"Dapple_Dualies.png",
          "name":"Dapple Dualies",
          "subweapon":"Squid Beakon"
       },
       {
          "specialweapon":"Splashdown",
          "imagename":"Dark_Tetra_Dualies.png",
          "name":"Dark Tetra Dualies",
          "subweapon":"Autobomb"
       },
       {
          "specialweapon":"Tenta Missiles",
          "imagename":"Dualie_Squelchers.png",
          "name":"Dualie Squelchers",
          "subweapon":"Point Sensor"
       },
       {
          "specialweapon":"Sting Ray",
          "imagename":"Dynamo_Roller.png",
          "name":"Dynamo Roller",
          "subweapon":"Ink Mine"
       },
       {
          "specialweapon":"Ink Storm",
          "imagename":"E-liter_4K_Scope.png",
          "name":"E-liter 4K Scope",
          "subweapon":"Ink Mine"
       },
       {
          "specialweapon":"Ink Storm",
          "imagename":"E-liter_4K.png",
          "name":"E-liter 4K",
          "subweapon":"Ink Mine"
       },
       {
          "specialweapon":"Inkjet",
          "imagename":"Enperry_Splat_Dualies.png",
          "name":"Enperry Splat Dualies",
          "subweapon":"Curling Bomb"
       },
       {
          "specialweapon":"Bubble Blower",
          "imagename":"Explosher.png",
          "name":"Explosher",
          "subweapon":"Sprinkler"
       },
       {
          "specialweapon":"Suction-Bomb Launcher",
          "imagename":"Firefin_Splat_Charger.png",
          "name":"Firefin Splat Charger",
          "subweapon":"Splash Wall"
       },
       {
          "specialweapon":"Suction-Bomb Launcher",
          "imagename":"Firefin_Splatterscope.png",
          "name":"Firefin Splatterscope",
          "subweapon":"Splash Wall"
       },
       {
          "specialweapon":"Splat-Bomb Launcher",
          "imagename":"Flingza_Roller.png",
          "name":"Flingza Roller",
          "subweapon":"Splash Wall"
       },
       {
          "specialweapon":"Tenta Missiles",
          "imagename":"Foil_Flingza_Roller.png",
          "name":"Foil Flingza Roller",
          "subweapon":"Suction Bomb"
       },
       {
          "specialweapon":"Bubble Blower",
          "imagename":"Foil_Squeezer.png",
          "name":"Foil Squeezer",
          "subweapon":"Splat Bomb"
       },
       {
          "specialweapon":"Bubble Blower",
          "imagename":"Forge_Splattershot_Pro.png",
          "name":"Forge Splattershot Pro",
          "subweapon":"Suction Bomb"
       },
       {
          "specialweapon":"Inkjet",
          "imagename":"Fresh_Squiffer.png",
          "name":"Fresh Squiffer",
          "subweapon":"Suction Bomb"
       },
       {
          "specialweapon":"Baller",
          "imagename":"Glooga_Dualies_Deco.png",
          "name":"Glooga Dualies Deco",
          "subweapon":"Splash Wall"
       },
       {
          "specialweapon":"Inkjet",
          "imagename":"Glooga_Dualies.png",
          "name":"Glooga Dualies",
          "subweapon":"Ink Mine"
       },
       {
          "specialweapon":"Ink Armor",
          "imagename":"Gold_Dynamo_Roller.png",
          "name":"Gold Dynamo Roller",
          "subweapon":"Splat Bomb"
       },
       {
          "specialweapon":"Splashdown",
          "imagename":"Goo_Tuber.png",
          "name":"Goo Tuber",
          "subweapon":"Suction Bomb"
       },
       {
          "specialweapon":"Tenta Missiles",
          "imagename":"Grim_Range_Blaster.png",
          "name":"Grim Range Blaster",
          "subweapon":"Burst Bomb"
       },
       {
          "specialweapon":"Ink Armor",
          "imagename":"H-3_Nozzlenose_D.png",
          "name":"H-3 Nozzlenose D",
          "subweapon":"Suction Bomb"
       },
       {
          "specialweapon":"Tenta Missiles",
          "imagename":"H-3_Nozzlenose.png",
          "name":"H-3 Nozzlenose",
          "subweapon":"Point Sensor"
       },
       {
          "specialweapon":"Bubble Blower",
          "imagename":"Heavy_Splatling_Deco.png",
          "name":"Heavy Splatling Deco",
          "subweapon":"Splash Wall"
       },
       {
          "specialweapon":"Booyah Bomb",
          "imagename":"Heavy_Splatling_Remix.png",
          "name":"Heavy Splatling Remix",
          "subweapon":"Point Sensor"
       },
       {
          "specialweapon":"Sting Ray",
          "imagename":"Heavy_Splatling.png",
          "name":"Heavy Splatling",
          "subweapon":"Sprinkler"
       },
       {
          "specialweapon":"Splashdown",
          "imagename":"Hero_Blaster_Replica.png",
          "name":"Hero Blaster Replica",
          "subweapon":"Toxic Mist"
       },
       {
          "specialweapon":"Ink Storm",
          "imagename":"Hero_Brella_Replica.png",
          "name":"Hero Brella Replica",
          "subweapon":"Sprinkler"
       },
       {
          "specialweapon":"Sting Ray",
          "imagename":"Hero_Charger_Replica.png",
          "name":"Hero Charger Replica",
          "subweapon":"Splat Bomb"
       },
       {
          "specialweapon":"Tenta Missiles",
          "imagename":"Hero_Dualie_Replicas.png",
          "name":"Hero Dualie Replicas",
          "subweapon":"Burst Bomb"
       },
       {
          "specialweapon":"Splashdown",
          "imagename":"Hero_Roller_Replica.png",
          "name":"Hero Roller Replica",
          "subweapon":"Curling Bomb"
       },
       {
          "specialweapon":"Splashdown",
          "imagename":"Hero_Shot_Replica.png",
          "name":"Hero Shot Replica",
          "subweapon":"Burst Bomb"
       },
       {
          "specialweapon":"Tenta Missiles",
          "imagename":"Hero_Slosher_Replica.png",
          "name":"Hero Slosher Replica",
          "subweapon":"Suction Bomb"
       },
       {
          "specialweapon":"Sting Ray",
          "imagename":"Hero_Splatling_Replica.png",
          "name":"Hero Splatling Replica",
          "subweapon":"Sprinkler"
       },
       {
          "specialweapon":"Inkjet",
          "imagename":"Herobrush_Replica.png",
          "name":"Herobrush Replica",
          "subweapon":"Autobomb"
       },
       {
          "specialweapon":"Splashdown",
          "imagename":"Hydra_Splatling.png",
          "name":"Hydra Splatling",
          "subweapon":"Autobomb"
       },
       {
          "specialweapon":"Baller",
          "imagename":"Inkbrush_Nouveau.png",
          "name":"Inkbrush Nouveau",
          "subweapon":"Ink Mine"
       },
       {
          "specialweapon":"Splashdown",
          "imagename":"Inkbrush.png",
          "name":"Inkbrush",
          "subweapon":"Splat Bomb"
       },
       {
          "specialweapon":"Tenta Missiles",
          "imagename":"Jet_Squelcher.png",
          "name":"Jet Squelcher",
          "subweapon":"Toxic Mist"
       },
       {
          "specialweapon":"Booyah Bomb",
          "imagename":"Kensa_52_Gal.png",
          "name":"Kensa .52 Gal",
          "subweapon":"Splash Wall"
       },
       {
          "specialweapon":"Baller",
          "imagename":"Kensa_Charger.png",
          "name":"Kensa Charger",
          "subweapon":"Sprinkler"
       },
       {
          "specialweapon":"Booyah Bomb",
          "imagename":"Kensa_Dynamo_Roller.png",
          "name":"Kensa Dynamo Roller",
          "subweapon":"Sprinkler"
       },
       {
          "specialweapon":"Ink Armor",
          "imagename":"Kensa_Glooga_Dualies.png",
          "name":"Kensa Glooga Dualies",
          "subweapon":"Fizzy Bomb"
       },
       {
          "specialweapon":"Ultra Stamp",
          "imagename":"Kensa_L-3_Nozzlenose.png",
          "name":"Kensa L-3 Nozzlenose",
          "subweapon":"Splash Wall"
       },
       {
          "specialweapon":"Ink Storm",
          "imagename":"Kensa_Luna_Blaster.png",
          "name":"Kensa Luna Blaster",
          "subweapon":"Fizzy Bomb"
       },
       {
          "specialweapon":"Ultra Stamp",
          "imagename":"Kensa_Mini_Splatling.png",
          "name":"Kensa Mini Splatling",
          "subweapon":"Toxic Mist"
       },
       {
          "specialweapon":"Ultra Stamp",
          "imagename":"Kensa_Octobrush.png",
          "name":"Kensa Octobrush",
          "subweapon":"Suction Bomb"
       },
       {
          "specialweapon":"Baller",
          "imagename":"Kensa_Rapid_Blaster.png",
          "name":"Kensa Rapid Blaster",
          "subweapon":"Torpedo"
       },
       {
          "specialweapon":"Splashdown",
          "imagename":"Kensa_Sloshing_Machine.png",
          "name":"Kensa Sloshing Machine",
          "subweapon":"Fizzy Bomb"
       },
       {
          "specialweapon":"Baller",
          "imagename":"Kensa_Splat_Dualies.png",
          "name":"Kensa Splat Dualies",
          "subweapon":"Suction Bomb"
       },
       {
          "specialweapon":"Bubble Blower",
          "imagename":"Kensa_Splat_Roller.png",
          "name":"Kensa Splat Roller",
          "subweapon":"Splat Bomb"
       },
       {
          "specialweapon":"Baller",
          "imagename":"Kensa_Splatterscope.png",
          "name":"Kensa Splatterscope",
          "subweapon":"Sprinkler"
       },
       {
          "specialweapon":"Bubble Blower",
          "imagename":"Kensa_Splattershot_Jr.png",
          "name":"Kensa Splattershot Jr.",
          "subweapon":"Torpedo"
       },
       {
          "specialweapon":"Booyah Bomb",
          "imagename":"Kensa_Splattershot_Pro.png",
          "name":"Kensa Splattershot Pro",
          "subweapon":"Splat Bomb"
       },
       {
          "specialweapon":"Tenta Missiles",
          "imagename":"Kensa_Splattershot.png",
          "name":"Kensa Splattershot",
          "subweapon":"Suction Bomb"
       },
       {
          "specialweapon":"Ink Armor",
          "imagename":"Kensa_Undercover_Brella.png",
          "name":"Kensa Undercover Brella",
          "subweapon":"Torpedo"
       },
       {
          "specialweapon":"Baller",
          "imagename":"Krak-On_Splat_Roller.png",
          "name":"Krak-On Splat Roller",
          "subweapon":"Squid Beakon"
       },
       {
          "specialweapon":"Inkjet",
          "imagename":"L-3_Nozzlenose_D.png",
          "name":"L-3 Nozzlenose D",
          "subweapon":"Burst Bomb"
       },
       {
          "specialweapon":"Baller",
          "imagename":"L-3_Nozzlenose.png",
          "name":"L-3 Nozzlenose",
          "subweapon":"Curling Bomb"
       },
       {
          "specialweapon":"Autobomb Launcher",
          "imagename":"Light_Tetra_Dualies.png",
          "name":"Light Tetra Dualies",
          "subweapon":"Sprinkler"
       },
       {
          "specialweapon":"Suction-Bomb Launcher",
          "imagename":"Luna_Blaster_Neo.png",
          "name":"Luna Blaster Neo",
          "subweapon":"Ink Mine"
       },
       {
          "specialweapon":"Baller",
          "imagename":"Luna_Blaster.png",
          "name":"Luna Blaster",
          "subweapon":"Splat Bomb"
       },
       {
          "specialweapon":"Tenta Missiles",
          "imagename":"Mini_Splatling.png",
          "name":"Mini Splatling",
          "subweapon":"Burst Bomb"
       },
       {
          "specialweapon":"Ink Storm",
          "imagename":"N-ZAP_83.png",
          "name":"N-ZAP '83",
          "subweapon":"Sprinkler"
       },
       {
          "specialweapon":"Ink Armor",
          "imagename":"N-ZAP_85.png",
          "name":"N-ZAP '85",
          "subweapon":"Suction Bomb"
       },
       {
          "specialweapon":"Tenta Missiles",
          "imagename":"N-ZAP_89.png",
          "name":"N-ZAP '89",
          "subweapon":"Autobomb"
       },
       {
          "specialweapon":"Baller",
          "imagename":"Nautilus_47.png",
          "name":"Nautilus 47",
          "subweapon":"Point Sensor"
       },
       {
          "specialweapon":"Inkjet",
          "imagename":"Nautilus_79.png",
          "name":"Nautilus 79",
          "subweapon":"Suction Bomb"
       },
       {
          "specialweapon":"Suction-Bomb Launcher",
          "imagename":"Neo_Splash-o-matic.png",
          "name":"Neo Splash-o-matic",
          "subweapon":"Burst Bomb"
       },
       {
          "specialweapon":"Tenta Missiles",
          "imagename":"Neo_Sploosh-o-matic.png",
          "name":"Neo Sploosh-o-matic",
          "subweapon":"Squid Beakon"
       },
       {
          "specialweapon":"Baller",
          "imagename":"New_Squiffer.png",
          "name":"New Squiffer",
          "subweapon":"Autobomb"
       },
       {
          "specialweapon":"Inkjet",
          "imagename":"Octo_Shot_Replica.png",
          "name":"Octo Shot Replica",
          "subweapon":"Splat Bomb"
       },
       {
          "specialweapon":"Tenta Missiles",
          "imagename":"Octobrush_Nouveau.png",
          "name":"Octobrush Nouveau",
          "subweapon":"Squid Beakon"
       },
       {
          "specialweapon":"Inkjet",
          "imagename":"Octobrush.png",
          "name":"Octobrush",
          "subweapon":"Autobomb"
       },
       {
          "specialweapon":"Ink Armor",
          "imagename":"Permanent_Inkbrush.png",
          "name":"Permanent Inkbrush",
          "subweapon":"Sprinkler"
       },
       {
          "specialweapon":"Ink Storm",
          "imagename":"Range_Blaster.png",
          "name":"Range Blaster",
          "subweapon":"Suction Bomb"
       },
       {
          "specialweapon":"Inkjet",
          "imagename":"Rapid_Blaster_Deco.png",
          "name":"Rapid Blaster Deco",
          "subweapon":"Suction Bomb"
       },
       {
          "specialweapon":"Ink Armor",
          "imagename":"Rapid_Blaster_Pro_Deco.png",
          "name":"Rapid Blaster Pro Deco",
          "subweapon":"Splash Wall"
       },
       {
          "specialweapon":"Ink Storm",
          "imagename":"Rapid_Blaster_Pro.png",
          "name":"Rapid Blaster Pro",
          "subweapon":"Toxic Mist"
       },
       {
          "specialweapon":"Splat-Bomb Launcher",
          "imagename":"Rapid_Blaster.png",
          "name":"Rapid Blaster",
          "subweapon":"Ink Mine"
       },
       {
          "specialweapon":"Baller",
          "imagename":"Slosher_Deco.png",
          "name":"Slosher Deco",
          "subweapon":"Sprinkler"
       },
       {
          "specialweapon":"Tenta Missiles",
          "imagename":"Slosher.png",
          "name":"Slosher",
          "subweapon":"Suction Bomb"
       },
       {
          "specialweapon":"Splat-Bomb Launcher",
          "imagename":"Sloshing_Machine_Neo.png",
          "name":"Sloshing Machine Neo",
          "subweapon":"Point Sensor"
       },
       {
          "specialweapon":"Sting Ray",
          "imagename":"Sloshing_Machine.png",
          "name":"Sloshing Machine",
          "subweapon":"Autobomb"
       },
       {
          "specialweapon":"Burst-Bomb Launcher",
          "imagename":"Soda_Slosher.png",
          "name":"Soda Slosher",
          "subweapon":"Splat Bomb"
       },
       {
          "specialweapon":"Splat-Bomb Launcher",
          "imagename":"Sorella_Brella.png",
          "name":"Sorella Brella",
          "subweapon":"Autobomb"
       },
       {
          "specialweapon":"Inkjet",
          "imagename":"Splash-o-matic.png",
          "name":"Splash-o-matic",
          "subweapon":"Toxic Mist"
       },
       {
          "specialweapon":"Ink Storm",
          "imagename":"Splat_Brella.png",
          "name":"Splat Brella",
          "subweapon":"Sprinkler"
       },
       {
          "specialweapon":"Sting Ray",
          "imagename":"Splat_Charger.png",
          "name":"Splat Charger",
          "subweapon":"Splat Bomb"
       },
       {
          "specialweapon":"Tenta Missiles",
          "imagename":"Splat_Dualies.png",
          "name":"Splat Dualies",
          "subweapon":"Burst Bomb"
       },
       {
          "specialweapon":"Splashdown",
          "imagename":"Splat_Roller.png",
          "name":"Splat Roller",
          "subweapon":"Curling Bomb"
       },
       {
          "specialweapon":"Sting Ray",
          "imagename":"Splatterscope.png",
          "name":"Splatterscope",
          "subweapon":"Splat Bomb"
       },
       {
          "specialweapon":"Ink Armor",
          "imagename":"Splattershot_Jr.png",
          "name":"Splattershot Jr.",
          "subweapon":"Splat Bomb"
       },
       {
          "specialweapon":"Ink Storm",
          "imagename":"Splattershot_Pro.png",
          "name":"Splattershot Pro",
          "subweapon":"Point Sensor"
       },
       {
          "specialweapon":"Splashdown",
          "imagename":"Splattershot.png",
          "name":"Splattershot",
          "subweapon":"Burst Bomb"
       },
       {
          "specialweapon":"Ultra Stamp",
          "imagename":"Sploosh-o-matic_7.png",
          "name":"Sploosh-o-matic 7",
          "subweapon":"Splat Bomb"
       },
       {
          "specialweapon":"Splashdown",
          "imagename":"Sploosh-o-matic.png",
          "name":"Sploosh-o-matic",
          "subweapon":"Curling Bomb"
       },
       {
          "specialweapon":"Sting Ray",
          "imagename":"Squeezer.png",
          "name":"Squeezer",
          "subweapon":"Splash Wall"
       },
       {
          "specialweapon":"Bubble Blower",
          "imagename":"Tenta_Brella.png",
          "name":"Tenta Brella",
          "subweapon":"Squid Beakon"
       },
       {
          "specialweapon":"Ultra Stamp",
          "imagename":"Tenta_Camo_Brella.png",
          "name":"Tenta Camo Brella",
          "subweapon":"Ink Mine"
       },
       {
          "specialweapon":"Curling-Bomb Launcher",
          "imagename":"Tenta_Sorella_Brella.png",
          "name":"Tenta Sorella Brella",
          "subweapon":"Splash Wall"
       },
       {
          "specialweapon":"Inkjet",
          "imagename":"Tentatek_Splattershot.png",
          "name":"Tentatek Splattershot",
          "subweapon":"Splat Bomb"
       },
       {
          "specialweapon":"Ink Storm",
          "imagename":"Tri-Slosher_Nouveau.png",
          "name":"Tri-Slosher Nouveau",
          "subweapon":"Splat Bomb"
       },
       {
          "specialweapon":"Ink Armor",
          "imagename":"Tri-Slosher.png",
          "name":"Tri-Slosher",
          "subweapon":"Burst Bomb"
       },
       {
          "specialweapon":"Splashdown",
          "imagename":"Undercover_Brella.png",
          "name":"Undercover Brella",
          "subweapon":"Ink Mine"
       },
       {
          "specialweapon":"Baller",
          "imagename":"Undercover_Sorella_Brella.png",
          "name":"Undercover Sorella Brella",
          "subweapon":"Splat Bomb"
       },
       {
          "specialweapon":"Ink Storm",
          "imagename":"Zink_Mini_Splatling.png",
          "name":"Zink Mini Splatling",
          "subweapon":"Curling Bomb"
       }
    ]
 }